polars_random-0.3.2.dist-info/METADATA
polars_random-0.3.2.dist-info/WHEEL
polars_random-0.3.2.dist-info/licenses/LICENSE
polars_random/__init__.py
polars_random/_internal.pyi
polars_random/typing.py
polars_random/_internal.abi3.so
polars_random-0.3.2.dist-info/RECORD
