Metadata-Version: 2.4
Name: polars-random
Version: 0.3.2
Requires-Dist: polars>=1.0.0
License-File: LICENSE
Summary: Polars plugin for generating random distributions
Author-email: Diego Garcia Lozano <diegoglozano96@gmail.com>
License: MIT
Requires-Python: >=3.9
